filechat/__init__.py
filechat/chat.py
filechat/config.py
filechat/embedder.py
filechat/index.py
filechat/tools.py
filechat/tui.py
filechat/utils.py
filechat/watcher.py
filechat-0.4.0.dist-info/METADATA
filechat-0.4.0.dist-info/WHEEL
filechat-0.4.0.dist-info/entry_points.txt
filechat-0.4.0.dist-info/RECORD
