Metadata-Version: 2.4
Name: filechat
Version: 0.4.0
Summary: A local read-only AI coding assistant
Author-email: Milos Svana <milos@svana.name>
License-Expression: MIT
Requires-Python: >=3.12
Requires-Dist: einops>=0.8.1
Requires-Dist: faiss-cpu>=1.11.0.post1
Requires-Dist: mistralai>=1.9.3
Requires-Dist: onnxruntime>=1.22.1
Requires-Dist: openai>=1.109.0
Requires-Dist: pip-system-certs>=5.2
Requires-Dist: pydantic>=2.11.7
Requires-Dist: rich>=14.1.0
Requires-Dist: textual>=5.3.0
Requires-Dist: tokenizers>=0.21.4
Requires-Dist: tqdm>=4.67.1
Requires-Dist: watchdog>=6.0.0
Provides-Extra: cuda
Requires-Dist: nvidia-cublas-cu12; extra == 'cuda'
Requires-Dist: nvidia-cuda-nvrtc-cu12; extra == 'cuda'
Requires-Dist: nvidia-cudnn-cu12; extra == 'cuda'
Requires-Dist: nvidia-cufft-cu12; extra == 'cuda'
Requires-Dist: nvidia-curand-cu12; extra == 'cuda'
Requires-Dist: onnxruntime-gpu; extra == 'cuda'
Provides-Extra: xpu
Requires-Dist: onnxruntime-openvino; extra == 'xpu'
